pitches/__init__.py
pitches/pitches.py
pitches-0.1.0.dist-info/METADATA
pitches-0.1.0.dist-info/WHEEL
pitches-0.1.0.dist-info/top_level.txt
pitches-0.1.0.dist-info/RECORD
